CHANGELOG.txt
MANIFEST.in
README.txt
setup.py
Kaone_basic_cal/__init__.py
Kaone_basic_cal.egg-info/PKG-INFO
Kaone_basic_cal.egg-info/SOURCES.txt
Kaone_basic_cal.egg-info/dependency_links.txt
Kaone_basic_cal.egg-info/top_level.txt