Metadata-Version: 1.1
Name: Kaone-basic-cal
Version: 0.0.1
Summary: a basic calculator
Home-page: UNKNOWN
Author: Kaone Bogopa
Author-email: UNKNOWN
License: MIT
Keywords: calculator
Platform: UNKNOWN
Classifier: Development Status :: 5 - Production/Stable
Classifier: Operating System :: Microsoft :: Windows :: Windows 10
Classifier: License :: OSI Approved :: MIT License
Classifier:  Programming Language :: Python :: 3
